sas2db/__init__.py
sas2db/run.py
sas2db/test_run.py
sas2sqlite/__init__.py
sas2sqlite/run.py
sas2sqlite/test_run.py
sas2db-0.2.1.dist-info/LICENSE.md
sas2db-0.2.1.dist-info/METADATA
sas2db-0.2.1.dist-info/WHEEL
sas2db-0.2.1.dist-info/entry_points.txt
sas2db-0.2.1.dist-info/top_level.txt
sas2db-0.2.1.dist-info/RECORD
