Metadata-Version: 2.1
Name: sas2db
Version: 0.2.1
Summary: Import SAS files to SQL databases
Home-page: https://github.com/XDgov/sas2db
Author: Aidan Feldman
Author-email: aidan.l.feldman@census.gov
License: UNKNOWN
Platform: UNKNOWN
Classifier: Development Status :: 3 - Alpha
Classifier: Environment :: Console
Classifier: License :: CC0 1.0 Universal (CC0 1.0) Public Domain Dedication
Classifier: Operating System :: OS Independent
Classifier: Programming Language :: Python :: 3
Requires-Python: >=3
Requires-Dist: inflection (<1,>0.3)
Requires-Dist: pandas (<1,>0.24)
Requires-Dist: sqlalchemy (<2,>1.3)
